SearchProblemsAI/__init__.py
SearchProblemsAI/utils.py
SearchProblemsAI/search_algorithms/MCTS.py
SearchProblemsAI/search_algorithms/__init__.py
SearchProblemsAI/search_algorithms/basic_algos.py
SearchProblemsAI/search_algorithms/search_algorithm.py
SearchProblemsAI/search_problems/FindCandy.py
SearchProblemsAI/search_problems/Tree.py
SearchProblemsAI/search_problems/__init__.py
SearchProblemsAI/search_problems/search_problem.py
example/a_non_deterministic_nav_problem.py
example/a_sensorless_nav_problem.py
example/mcts_for_tree.py
example/navigation.py
SearchProblemsAI-2.0.dist-info/LICENSE
SearchProblemsAI-2.0.dist-info/METADATA
SearchProblemsAI-2.0.dist-info/WHEEL
SearchProblemsAI-2.0.dist-info/top_level.txt
SearchProblemsAI-2.0.dist-info/RECORD
