Metadata-Version: 2.1
Name: SearchProblemsAI
Version: 2.0
Summary: SearchProblemsAI is a library of AI agents for Search Problems.
Home-page: https://github.com/tboulet/AI-Agents-for-Search-Problems
Author: Timothé Boulet
Author-email: timothe.boulet0@gmail.com
License: MIT
License-File: LICENSE
